{
  "Group": "P",
  "Entries": 4,
  "Words": [
    {
      "EnglishWord": "patience is a plaster for all sores",
      "Meanings": [
        "صبر",
        "درمان هر دردیست",
        "منبع: zabansara. org"
      ]
    },
    {
      "EnglishWord": "pleasant hours fly fast",
      "Meanings": [
        "لحظات خوشی زود می‌گذرد",
        "منبع: zabansara. org"
      ]
    },
    {
      "EnglishWord": "property acquired free of cost is sweeter than hon",
      "Meanings": [
        "مال مفت از عسل شیرین‌تر است",
        "منبع: zabansara. org"
      ]
    },
    {
      "EnglishWord": "pry not into the affair of others",
      "Meanings": [
        "در کار دیگران مداخله مکن",
        "منبع: zabansara. org"
      ]
    }
  ]
}