{
  "Group": "J",
  "Entries": 22,
  "Words": [
    {
      "EnglishWord": "jack box",
      "Meanings": [
        "جعبه تقسیم تلفن"
      ]
    },
    {
      "EnglishWord": "jack in the box",
      "Meanings": [
        "جعبه ای که چون در انرا میگشایند ادمکی از ان خارج شود"
      ]
    },
    {
      "EnglishWord": "jamshidi naorozi, norooz",
      "Meanings": [
        "نوروز"
      ]
    },
    {
      "EnglishWord": "january",
      "Meanings": [
        "ژانویه"
      ]
    },
    {
      "EnglishWord": "jelly, gelly, cream",
      "Meanings": [
        "ژله"
      ]
    },
    {
      "EnglishWord": "jelly-fish float",
      "Meanings": [
        "شناور شدن در اب با دست و پای دراز"
      ]
    },
    {
      "EnglishWord": "jew",
      "Meanings": [
        "یهودی"
      ]
    },
    {
      "EnglishWord": "jewel-box",
      "Meanings": [
        "جعبه جواهر"
      ]
    },
    {
      "EnglishWord": "joan silver pin",
      "Meanings": [
        "خشخاش"
      ]
    },
    {
      "EnglishWord": "job control language",
      "Meanings": [
        "جی سی ال",
        "زبان کنترل برنامه",
        "زبان کنترل کار"
      ]
    },
    {
      "EnglishWord": "job definition",
      "Meanings": [
        "تعریف برنامه"
      ]
    },
    {
      "EnglishWord": "journal of the iranian mathematical soci",
      "Meanings": [
        "ماهنامه انجمن ریاضی ایران"
      ]
    },
    {
      "EnglishWord": "judge made law",
      "Meanings": [
        "نظام حقوقی مبتنی بر سوابق قضایی و ارا محاکم"
      ]
    },
    {
      "EnglishWord": "judo",
      "Meanings": [
        "جودو"
      ]
    },
    {
      "EnglishWord": "july",
      "Meanings": [
        "جولای"
      ]
    },
    {
      "EnglishWord": "jump stop",
      "Meanings": [
        "توقف ناگهانی با پرش بهوا وچرخش"
      ]
    },
    {
      "EnglishWord": "junction box",
      "Meanings": [
        "جعبه اتصال"
      ]
    },
    {
      "EnglishWord": "juncture",
      "Meanings": [
        "اتصال"
      ]
    },
    {
      "EnglishWord": "junto",
      "Meanings": [
        "حزب"
      ]
    },
    {
      "EnglishWord": "jury-box",
      "Meanings": [
        "جایگاه ویژه هییت منصفه"
      ]
    },
    {
      "EnglishWord": "just a moment please",
      "Meanings": [
        "لطفا یک دقیقه صبر کنید"
      ]
    },
    {
      "EnglishWord": "justice, equity",
      "Meanings": [
        "دادگستری"
      ]
    }
  ]
}